{
    "id": 116501604,
    "name": "cyrillic wave",
    "author": "SpaceID",
    "creators": [],
    "verifier": "SpaceID",
    "verification": "https://www.youtube.com/watch?v=sirDyT-J5co",
    "percentToQualify": "100",
    "password": "Free To Copy",
    "records": [
        {
            "user": "DALUCKYCARPET0",
            "link": "https://www.youtube.com/watch?v=hB-BldbuGfo",
            "percent": 100,
            "hz": 240
        },
        {
            "user": "BlueGamer",
            "link": "https://www.youtube.com/watch?v=8-pfM4Rc5b8",
            "percent": 100,
            "hz": 240
        }
    ]
}
