{
    "id": 115054534,
    "name": "Wavey ",
    "author": "CuteAxi",
    "creators": ["CuteAxi"],
    "verifier": "CuteAxi",
    "verification": "https://www.youtube.com/watch?v=KqsfBn97K8E",
    "percentToQualify": "100",
    "password": "Free To Copy",
    "records": [
        {
            "user": "ThorDasher",
            "link": "https://www.youtube.com/watch?v=o8ucYbrpTC0",
            "percent": 100,
            "hz": 60
        },
        {
            "user": "Hydrate",
            "link": "https://www.youtube.com/watch?v=_b5OJh96RVE",
            "percent": 100,
            "hz": 240
        },    
        {
            "user": "Storm",
            "link": "https://youtu.be/Pcz6AFNPmQw",
            "percent": 100,
            "hz": 240
        },   
        {
            "user": "tabby (you will be missed)",
            "link": "https://youtu.be/2SMetFbFxWI",
            "percent": 100,
            "hz": 60
        },
        {
            "user": "Mex",
            "link": "https://www.youtube.com/watch?v=nRLosDBG-CM",
            "percent": 100,
            "hz": 240
        },
          {
            "user": "ex66",
            "link": "https://www.youtube.com/watch?v=sio1-aMQEDE",
            "percent": 100,
            "hz": 120
        },
        {
            "user": "verseorfluuf",
            "link": "https://www.youtube.com/watch?v=iD9rTC-y_Es",
            "percent": 100,
            "hz": 240
        },
        {
            "user": "BlueGamer",
            "link": "https://www.youtube.com/watch?v=Eckkl3kGQf0",
            "percent": 100,
            "hz": 240
        },
        {
            "user": "DALUCKYCARPET0",
            "link": "https://www.youtube.com/watch?v=Xjg-79JWMPs",
            "percent": 100,
            "hz": 240
        },
        {
            "user": "Bubriz",
            "link": "https://youtu.be/TgDU_ni6hok",
            "percent": 100,
            "hz": 60
        },    
        {
            "user": "Lucy (tabbys blahaj)",
            "link": "https://youtu.be/pO0DtoISwV4",
            "percent": 100,
            "hz": 120
                    },
        {
            "user": "ggdotlol",
            "link": "https://www.youtube.com/watch?v=vdgJDKb2rKM",
            "percent": 100,
            "hz": 240
        }
    ]
}
